{"articles":{"/README.md":[],"/javascript/tip.md":[],"/nginx/nginx基础.md":["good","nginx"],"/nginx/nginx安装.md":[],"/nginx/nginx配置.md":[],"/reactjs/redux.md":[],"/reactjs/tip.md":[]},"tags":{"good":["/nginx/nginx基础.md"],"nginx":["/nginx/nginx基础.md"]},"tree":[{"hash":"4542be2db5e9f36a0d740733e59863b9","path":"/README.md","file":"README"},{"path":"/javascript","file":"javascript","children":[{"hash":"5a0e22b6913d1e8d0d6d5e1b397456b8","path":"/javascript/tip.md","file":"tip"}]},{"path":"/nginx","file":"nginx","children":[{"hash":"38fab387632daaf5469cc13d840dbeaf","path":"/nginx/nginx基础.md","file":"nginx基础"},{"hash":"c6c78b700f6423e74e54209894fd84ab","path":"/nginx/nginx安装.md","file":"nginx安装"},{"hash":"6881b798cf253ae09aab37b93ea52145","path":"/nginx/nginx配置.md","file":"nginx配置"}]},{"path":"/reactjs","file":"reactjs","children":[{"hash":"f17d23be2ce430f6a485ce5f7e2f87b3","path":"/reactjs/redux.md","file":"redux"},{"hash":"28786c38167bde297aa717d92760975d","path":"/reactjs/tip.md","file":"tip"}]}]}